Workbook

Sheet Overview
A1: APEX — Talent, Alumni & Network
A2: Yearly plan · September 2026 – August 2027
A3: Owner: Nadav Delgo · Reviewed weekly with Avishag · Built from the role definition (§ references point at it)
A5: אתה ה־Human Node של APEX. וככל שאתה מצליח יותר בתפקיד, אני צריכה להיות פחות באמצע.
A6: — the role definition, §25
A8: Where things stand
A9: =COUNTA(Roster!$B$2:$B$98) | C9: =COUNTA('Call Schedule'!$E$2:$E$190) | E9: =COUNTIF('Call Schedule'!$L$2:$L$190,"done") | G9: =COUNTA(Roster!$R$2:$R$98)
A10: Alumni | C10: Conversations planned | E10: Done so far | G10: Roster rows with a next action
A13: Who the alumni are
A14: Tier sets call frequency and nothing else. It is not a ranking, and the matching engine ignores it — a tier-C engineer at Wiz is still a first-class referral path into Wiz.
A16: Tier | B16: Who | C16: Calls/yr | D16: People | E16: Calls/yr total | F16: Done | G16: % done
A17: A | B17: Founders, stealth builders, people at a transition point (§5) | C17: 3 | D17: =COUNTIF(Roster!$K$2:$K$98,$A17) | E17: =COUNTIF('Call Schedule'!$G$2:$G$190,$A17) | F17: =COUNTIFS('Call Schedule'!$G$2:$G$190,$A17,'Call Schedule'!$L$2:$L$190,"done") | G17: =IF($E17=0,0,$F17/$E17)
A18: B | B18: Seniority or research standing — office hours, referrals, intros | C18: 2 | D18: =COUNTIF(Roster!$K$2:$K$98,$A18) | E18: =COUNTIF('Call Schedule'!$G$2:$G$190,$A18) | F18: =COUNTIFS('Call Schedule'!$G$2:$G$190,$A18,'Call Schedule'!$L$2:$L$190,"done") | G18: =IF($E18=0,0,$F18/$E18)
A19: C | B19: No verified role (the roll-up backlog) + slower-moving ICs | C19: 1 | D19: =COUNTIF(Roster!$K$2:$K$98,$A19) | E19: =COUNTIF('Call Schedule'!$G$2:$G$190,$A19) | F19: =COUNTIFS('Call Schedule'!$G$2:$G$190,$A19,'Call Schedule'!$L$2:$L$190,"done") | G19: =IF($E19=0,0,$F19/$E19)
A20: Total | D20: =SUM($D$17:$D$19) | E20: =SUM($E$17:$E$19) | F20: =SUM($F$17:$F$19) | G20: =IF($E20=0,0,$F20/$E20)
A22: Rotation: 3–4 conversations a week, Sunday to Wednesday, across 50 working weeks. Thursday stays clear for the weekly report. חגים are excluded — no call is scheduled on one.
A25: The year in four movements
A26: Quarter | B26: Theme | C26: The test it has to pass | D26: Calls | E26: Done | F26: % done
A27: Q1 · Sep–Nov 2026 | B27: Know them | C27: The 90-day test (§24) — every question answerable without asking anyone | D27: =COUNTIF('Call Schedule'!$D$2:$D$190,"Q1") | E27: =COUNTIFS('Call Schedule'!$D$2:$D$190,"Q1",'Call Schedule'!$L$2:$L$190,"done") | F27: =IF($D27=0,0,$E27/$D27)
A28: Q2 · Dec–Feb | B28: Harness them | C28: Alumni move from receiving value to giving it (§4) | D28: =COUNTIF('Call Schedule'!$D$2:$D$190,"Q2") | E28: =COUNTIFS('Call Schedule'!$D$2:$D$190,"Q2",'Call Schedule'!$L$2:$L$190,"done") | F28: =IF($D28=0,0,$E28/$D28)
A29: Q3 · Mar–May 2027 | B29: Compound | C29: Alumni-to-alumni introductions outnumber the ones Nadav brokers | D29: =COUNTIF('Call Schedule'!$D$2:$D$190,"Q3") | E29: =COUNTIFS('Call Schedule'!$D$2:$D$190,"Q3",'Call Schedule'!$L$2:$L$190,"done") | F29: =IF($D29=0,0,$E29/$D29)
A30: Q4 · Jun–Aug 2027 | B30: Institutionalise | C30: A month without Avishag, run for real — does the network still strengthen? | D30: =COUNTIF('Call Schedule'!$D$2:$D$190,"Q4") | E30: =COUNTIFS('Call Schedule'!$D$2:$D$190,"Q4",'Call Schedule'!$L$2:$L$190,"done") | F30: =IF($D30=0,0,$E30/$D30)
A33: How to use this workbook
A34: Yellow cells are yours to fill in. | B34: Everything else is generated from config/network/roster.csv and the call rotation, and is overwritten when the workbook is rebuilt.
A35: Call Schedule | B35: One row per planned conversation. Set Status to 'done' — the row turns green and every count above moves.
A36: Roster | B36: The source of truth for people. After each call fill Now, Needs, Can help, Last contact and above all NEXT ACTION.
A37: KPI Tracker | B37: Weekly numbers. The call counts and the funnel compute themselves; the rest you type.
A38: Q1 90-Day Test | B38: The eight questions §24 says must be answerable in ninety days.
A39: Projects | B39: Coffee Club, SF, Office Hours, Alumni Roll-Up — with dates.
A41: Example of a filled roster row
A42: Now / current goal | B42: Leaving Meta in November, starting a company
A43: Needs | B43: Technical co-founder; two intros in AI infra
A44: Can help with | B44: ML pipelines; interviewing; referrals into Meta
A45: Tie strength | B45: Engaged
A46: Last contact | B46: 14/09/2026
A47: Source | B47: call 14/09
A48: NEXT ACTION | B48: Intro to Guy Goldenberg (Wiz) on the ML infra opening
A49: Due | B49: 21/09/2026
A50: Illustration only — this is not a real alum, and no row like it exists in the Roster sheet.
A53: Where the data came from
A54: • Alumni: 97 rows from Apex_Master_150726.xlsx (cohort #1 26, #2 33, #3 38).
A55: • That sheet screened alumni against GPU-systems / power / real-time criteria for a hardware founding team. Its verdicts are preserved in the Roster's Source note column and are not used for tiering here.
A56: • Tiers, cadence, KPI targets and project definitions: config/network/network.yaml, derived from the role definition.
A57: • חגים read from the 'חגים בישראל' calendar, not inferred. Only Sep–Nov 2026 is filled in; extend cadence.off_days to cover the rest.
A58: • Open with Avishag: 97 alumni here vs 82 graduates in the Canon vs the 117 quoted to her on 26/08 — the funnel needs one denominator.

Sheet Call Schedule
A1: Date | B1: Day | C1: Wk | D1: Qtr | E1: Who | F1: Cohort | G1: Tier | H1: Channel | I1: What the call is for | J1: Phone | K1: Email | L1: Status | M1: Notes from the call
A2: 46271 | B2: Sun | C2: 1 | D2: Q1 | E2: Assaf Monsa | F2: #1 | G2: A | H2: phone | I2: Node candidate. What can they open for our alumni, and would they give office hours? | J2: +972544319991 | K2: assafmonsa@gmail.com
A3: 46272 | B3: Mon | C3: 1 | D3: Q1 | E3: Danny Grander | F3: #1 | G3: A | H3: phone | I3: Node candidate — founded Snyk. What can they open for our alumni, and would they give office hours? | J3: +972507616594 | K3: danny.grander@gmail.com
A4: 46273 | B4: Tue | C4: 1 | D4: Q1 | E4: Eldad Kepten | F4: #1 | G4: B | H4: linkedin | I4: What can they give — office hours, referrals, mentoring? And what do they need from us right now?
A5: 46274 | B5: Wed | C5: 1 | D5: Q1 | E5: Aviel Adler | F5: #1 | G5: C | H5: phone | I5: Stay current — what are they working on now, and what would help? | J5: +972549954666 | K5: avieladler@gmail.com
A6: 46279 | B6: Mon | C6: 2 | D6: Q1 | E6: Eyal Kraft | F6: #1 | G6: A | H6: linkedin | I6: Founding track — building this year? What is the blocker, is co-founder the gap, and who should they meet?
A7: 46280 | B7: Tue | C7: 2 | D7: Q1 | E7: Eran Hertzmann | F7: #1 | G7: B | H7: phone | I7: What can they give — office hours, referrals, mentoring? And what do they need from us right now? | J7: +972545424895 | K7: eran.hertzmann@gmail.com
A8: 46281 | B8: Wed | C8: 2 | D8: Q1 | E8: Gai Gutherz | F8: #1 | G8: B | H8: linkedin | I8: What can they give — office hours, referrals into Miggo, mentoring? And what do they need from us right now?
A9: 46282 | B9: Thu | C9: 2 | D9: Q1 | E9: Daniel Ohayon | F9: #1 | G9: C | H9: phone | I9: Stay current — what are they working on in research now, and what would help? | J9: +972524056440
A10: 46287 | B10: Tue | C10: 3 | D10: Q1 | E10: Inbal Beracha | F10: #1 | G10: A | H10: linkedin | I10: Founding track — building this year? What is the blocker, is co-founder the gap, and who should they meet?
A11: 46288 | B11: Wed | C11: 3 | D11: Q1 | E11: Meir Adest | F11: #1 | G11: A | H11: linkedin | I11: Node candidate. What can they open for our alumni, and would they give office hours?
A12: 46289 | B12: Thu | C12: 3 | D12: Q1 | E12: Michal Shilo | F12: #1 | G12: B | H12: phone | I12: What can they give — office hours, referrals, mentoring? And what do they need from us right now? | J12: +972524598022 | K12: michalshilo6@gmail.com
A13: 46299 | B13: Sun | C13: 4 | D13: Q1 | E13: Michael Kellner | F13: #1 | G13: A | H13: phone | I13: Node candidate — founded SendBlocks. What can they open for our alumni, and would they give office hours? | J13: +972545311213 | K13: mike53il@gmail.com
A14: 46300 | B14: Mon | C14: 4 | D14: Q1 | E14: Nadav Zemach | F14: #1 | G14: B | H14: linkedin | I14: What can they give — office hours, referrals, mentoring? And what do they need from us right now?
A15: 46301 | B15: Tue | C15: 4 | D15: Q1 | E15: Noy Duany | F15: #1 | G15: B | H15: linkedin | I15: What can they give — office hours, referrals into Hopper Security, mentoring? And what do they need from us right now?
A16: 46302 | B16: Wed | C16: 4 | D16: Q1 | E16: Dror Ben Eliezer | F16: #1 | G16: C | H16: linkedin | I16: Stay current — what are they working on in product-gtm now, and what would help?
A17: 46306 | B17: Sun | C17: 5 | D17: Q1 | E17: Uri Shaked | F17: #1 | G17: A | H17: linkedin | I17: Node candidate. What can they open for our alumni, and would they give office hours?
A18: 46307 | B18: Mon | C18: 5 | D18: Q1 | E18: Zvi Wexlstein | F18: #1 | G18: A | H18: email | I18: Transition point — what are they building or moving toward, what is the blocker, and who should they meet? | K18: zviwex@gmail.com
A19: 46308 | B19: Tue | C19: 5 | D19: Q1 | E19: Ohad Amosy | F19: #1 | G19: B | H19: linkedin | I19: What can they give — office hours, referrals, mentoring? And what do they need from us right now?
A20: 46309 | B20: Wed | C20: 5 | D20: Q1 | E20: Omer Hay | F20: #1 | G20: B | H20: linkedin | I20: What can they give — office hours, referrals, mentoring? And what do they need from us right now?
A21: 46313 | B21: Sun | C21: 6 | D21: Q1 | E21: Rami Anati | F21: #1 | G21: B | H21: linkedin | I21: What can they give — office hours, referrals, mentoring? And what do they need from us right now?
A22: 46314 | B22: Mon | C22: 6 | D22: Q1 | E22: Eran Hirsch | F22: #1 | G22: C | H22: phone | I22: Stay current — what are they working on in infra-systems now, and what would help? | J22: +972548303525 | K22: eranhirsch@gmail.com
A23: 46315 | B23: Tue | C23: 6 | D23: Q1 | E23: Almog Zer | F23: #2 | G23: A | H23: phone | I23: Founding track — building this year? What is the blocker, is co-founder the gap, and who should they meet? | J23: +972507363131 | K23: almogx3@gmail.com
A24: 46320 | B24: Sun | C24: 7 | D24: Q1 | E24: Roee Yaron | F24: #1 | G24: B | H24: linkedin | I24: What can they give — office hours, referrals into Ministry of Defense, mentoring? And what do they need from us right now?
A25: 46321 | B25: Mon | C25: 7 | D25: Q1 | E25: Nir Yaron | F25: #1 | G25: C | H25: linkedin | I25: Roll-up — no verified role on file. What are they doing now, where are they heading, and what do they need?
A26: 46323 | B26: Wed | C26: 7 | D26: Q1 | E26: Bar Matityahu | F26: #2 | G26: A | H26: phone | I26: Founding track — building this year? What is the blocker, is co-founder the gap, and who should they meet? | J26: +972525892000 | K26: barmatit@gmail.com
A27: 46324 | B27: Thu | C27: 7 | D27: Q1 | E27: Benny Rousso | F27: #2 | G27: A | H27: phone | I27: Node candidate — founded Xcardia. What can they open for our alumni, and would they give office hours? | J27: +972544345653 | K27: rousso.benny@gmail.com
A28: 46327 | B28: Sun | C28: 8 | D28: Q1 | E28: Ronen Tur | F28: #1 | G28: B | H28: linkedin | I28: What can they give — office hours, referrals, mentoring? And what do they need from us right now?
A29: 46328 | B29: Mon | C29: 8 | D29: Q1 | E29: Shachar Cohen | F29: #1 | G29: B | H29: linkedin | I29: What can they give — office hours, referrals, mentoring? And what do they need from us right now?
A30: 46329 | B30: Tue | C30: 8 | D30: Q1 | E30: Gal Wiernik | F30: #2 | G30: A | H30: phone | I30: Node candidate — founded Edwin. What can they open for our alumni, and would they give office hours? | J30: +972502338655 | K30: galwiernik@gmail.com
A31: 46330 | B31: Wed | C31: 8 | D31: Q1 | E31: Guy Yoshpe | F31: #2 | G31: A | H31: phone | I31: Founding track — building this year? What is the blocker, is co-founder the gap, and who should they meet? | J31: +972508717313 | K31: yoshpe@gmail.com
A32: 46334 | B32: Sun | C32: 9 | D32: Q1 | E32: Shai Elroy | F32: #1 | G32: B | H32: linkedin | I32: What can they give — office hours, referrals, mentoring? And what do they need from us right now?
A33: 46335 | B33: Mon | C33: 9 | D33: Q1 | E33: Hila Shmuel | F33: #2 | G33: A | H33: phone | I33: Node candidate — founded Cabinet (AI workspace). What can they open for our alumni, and would they give office hours? | J33: +972508871171 | K33: hila4321@gmail.com
A34: 46336 | B34: Tue | C34: 9 | D34: Q1 | E34: Aviel Zecharia | F34: #2 | G34: B | H34: phone | I34: What can they give — office hours, referrals into Palo Alto Networks, mentoring? And what do they need from us right now? | J34: +972547260058 | K34: avielz1199@gmail.com
A35: 46337 | B35: Wed | C35: 9 | D35: Q1 | E35: Benzion Kossowsky | F35: #2 | G35: C | H35: phone | I35: Stay current — what are they working on now, and what would help? | J35: +972543315821 | K35: benzionkossowsky@gmail.com
A36: 46341 | B36: Sun | C36: 10 | D36: Q1 | E36: Iddan Golomb | F36: #2 | G36: A | H36: phone | I36: Node candidate — founded Sayata. What can they open for our alumni, and would they give office hours? | J36: +972542421974 | K36: igolomb@gmail.com
A37: 46342 | B37: Mon | C37: 10 | D37: Q1 | E37: Jonathan Gilat | F37: #2 | G37: A | H37: phone | I37: Node candidate — founded Medida AI. What can they open for our alumni, and would they give office hours? | J37: +972528198278 | K37: jonathan@medida.ai
A38: 46343 | B38: Tue | C38: 10 | D38: Q1 | E38: Eyal Horowicz | F38: #2 | G38: B | H38: phone | I38: What can they give — office hours, referrals into Claroty (DS Team Leader per roster), mentoring? And what do they need from us right now? | J38: +972506228892 | K38: eyalhoro6@gmail.com
A39: 46344 | B39: Wed | C39: 10 | D39: Q1 | E39: Kfir Shoar | F39: #2 | G39: C | H39: linkedin | I39: Stay current — still at Cyera? What are they working on in security, and what would help?
A40: 46348 | B40: Sun | C40: 11 | D40: Q1 | E40: Liran Markin | F40: #2 | G40: A | H40: phone | I40: Node candidate — founded Edwin. What can they open for our alumni, and would they give office hours? | J40: +972544911254 | K40: liran.markin@gmail.com
A41: 46349 | B41: Mon | C41: 11 | D41: Q1 | E41: Michael Komraz | F41: #2 | G41: A | H41: phone | I41: Founding track — building this year? What is the blocker, is co-founder the gap, and who should they meet? | J41: +972544319975 | K41: mikomraz@gmail.com
A42: 46350 | B42: Tue | C42: 11 | D42: Q1 | E42: Gil Raytan | F42: #2 | G42: B | H42: phone | I42: What can they give — office hours, referrals into Remitly (AI/ML), mentoring? And what do they need from us right now? | J42: +972544322242 | K42: gil.raytan@gmail.com
A43: 46355 | B43: Sun | C43: 12 | D43: Q1 | E43: Mor Shemesh | F43: #2 | G43: A | H43: phone | I43: Founding track — building this year? What is the blocker, is co-founder the gap, and who should they meet? | J43: +972507711998 | K43: mor.m.shemesh@gmail.com
A44: 46356 | B44: Mon | C44: 12 | D44: Q1 | E44: Ido Kazma | F44: #2 | G44: B | H44: phone | I44: What can they give — office hours, referrals into Q.ai, mentoring? And what do they need from us right now? | J44: +972528584131 | K44: idokazma@gmail.com
A45: 46357 | B45: Tue | C45: 12 | D45: Q2 | E45: Ilan Voronel | F45: #2 | G45: B | H45: phone | I45: What can they give — office hours, referrals into Glassbox, mentoring? And what do they need from us right now? | J45: +972547397052 | K45: ilan.voronel@gmail.com
A46: 46358 | B46: Wed | C46: 12 | D46: Q2 | E46: Lior Lev Tov | F46: #2 | G46: C | H46: phone | I46: Stay current — still at Eon.io? What are they working on in infra-systems, and what would help? | J46: +972542267010 | K46: liorlevtov@gmail.com
A47: 46362 | B47: Sun | C47: 13 | D47: Q2 | E47: Roy Moshe | F47: #2 | G47: A | H47: phone | I47: Founding track — building this year? What is the blocker, is co-founder the gap, and who should they meet? | J47: +972546777815 | K47: roymoshe23@gmail.com
A48: 46363 | B48: Mon | C48: 13 | D48: Q2 | E48: Tomer Goren | F48: #2 | G48: A | H48: phone | I48: Founding track — building this year? What is the blocker, is co-founder the gap, and who should they meet? | J48: +972544744575 | K48: tomergoren99@gmail.com
A49: 46364 | B49: Tue | C49: 13 | D49: Q2 | E49: Michael Zuzovski | F49: #2 | G49: B | H49: phone | I49: What can they give — office hours, referrals into TAU (ex-Amazon), mentoring? And what do they need from us right now? | J49: +972527564010 | K49: giga123@gmail.com
A50: 46365 | B50: Wed | C50: 13 | D50: Q2 | E50: Michal Ran Shchory | F50: #2 | G50: C | H50: phone | I50: Stay current — still at Protai? What are they working on in ai-ml, and what would help? | J50: +972544443440 | K50: michalran95@gmail.com
A51: 46369 | B51: Sun | C51: 14 | D51: Q2 | E51: Omer Onn | F51: #2 | G51: B | H51: phone | I51: What can they give — office hours, referrals into Akeyless (ex-System Architect, DriveNets), mentoring? And what do they need from us right now? | J51: +972508112332 | K51: omeronn@gmail.com
... A57: 46378 | B57: Tue | C57: 15 | D57: Q2 | E57: Nadav Claude Cohen | F57: #3 | G57: A | H57: phone | I57: Founding track — building this year? What is the blocker, is co-founder the gap, and who should they meet? | J57: +972543134989 | K57: nadav.claude.cohen@gmail.com
A58: 46383 | B58: Sun | C58: 16 | D58: Q2 | E58: Shaked Yehezkel | F58: #2 | G58: B | H58: linkedin | I58: What can they give — office hours, referrals into TAU, mentoring? And what do they need from us right now?
A59: 46384 | B59: Mon | C59: 16 | D59: Q2 | E59: Sharon Brizinov | F59: #2 | G59: B | H59: phone | I59: What can they give — office hours, referrals, mentoring? And what do they need from us right now? | J59: +972544702148 | K59: sharon.brizinov@gmail.com
A60: 46385 | B60: Tue | C60: 16 | D60: Q2 | E60: Oren Fine | F60: #3 | G60: A | H60: phone | I60: Founding track — building this year? What is the blocker, is co-founder the gap, and who should they meet? | J60: +972586392129 | K60: orenfine@gmail.com
A61: 46386 | B61: Wed | C61: 16 | D61: Q2 | E61: Shlomo Lahav | F61: #3 | G61: A | H61: phone | I61: Node candidate — founded TrueNorth Systems. What can they open for our alumni, and would they give office hours? | J61: +972545330111 | K61: shlomo@lahavs.com
A62: 46390 | B62: Sun | C62: 17 | D62: Q2 | E62: Tzah Pahima | F62: #2 | G62: B | H62: phone | I62: What can they give — office hours, referrals into Orca Security, mentoring? And what do they need from us right now? | J62: +972538271198 | K62: tzahpahima123@gmail.com
A63: 46391 | B63: Mon | C63: 17 | D63: Q2 | E63: Yakov Kosoburd | F63: #2 | G63: B | H63: phone | I63: What can they give — office hours, referrals, mentoring? And what do they need from us right now? | J63: +972529508555 | K63: yakov.kosoburd@gmail.com
A64: 46392 | B64: Tue | C64: 17 | D64: Q2 | E64: Shachar Resisi | F64: #2 | G64: C | H64: phone | I64: Stay current — still at Vayyar Imaging? What are they working on in ai-ml, and what would help? | J64: +972542566787 | K64: shachar.resisi@gmail.com
A65: 46393 | B65: Wed | C65: 17 | D65: Q2 | E65: Yaniv Shaked | F65: #3 | G65: A | H65: phone | I65: Founding track — building this year? What is the blocker, is co-founder the gap, and who should they meet? | J65: +972525621097 | K65: yanivsh002@gmail.com
A66: 46397 | B66: Sun | C66: 18 | D66: Q2 | E66: Assaf Monsa | F66: #1 | G66: A | H66: phone | I66: Node candidate. What can they open for our alumni, and would they give office hours? | J66: +972544319991 | K66: assafmonsa@gmail.com
A67: 46398 | B67: Mon | C67: 18 | D67: Q2 | E67: Danny Grander | F67: #1 | G67: A | H67: phone | I67: Node candidate — founded Snyk. What can they open for our alumni, and would they give office hours? | J67: +972507616594 | K67: danny.grander@gmail.com
A68: 46399 | B68: Tue | C68: 18 | D68: Q2 | E68: Yuri Shapira | F68: #2 | G68: B | H68: phone | I68: What can they give — office hours, referrals into PureSec (Architect @ PAN per roster), mentoring? And what do they need from us right now? | J68: +972547225688 | K68: yurishapira@gmail.com
A69: 46400 | B69: Wed | C69: 18 | D69: Q2 | E69: Adi Cohen | F69: #3 | G69: C | H69: phone | I69: Roll-up — no verified role on file. What are they doing now, where are they heading, and what do they need? | J69: +972543990302 | K69: cohenadi02@gmail.com
A70: 46404 | B70: Sun | C70: 19 | D70: Q2 | E70: Eyal Kraft | F70: #1 | G70: A | H70: linkedin | I70: Founding track — building this year? What is the blocker, is co-founder the gap, and who should they meet?
A71: 46405 | B71: Mon | C71: 19 | D71: Q2 | E71: Inbal Beracha | F71: #1 | G71: A | H71: linkedin | I71: Founding track — building this year? What is the blocker, is co-founder the gap, and who should they meet?
A72: 46406 | B72: Tue | C72: 19 | D72: Q2 | E72: Alon Wolf | F72: #3 | G72: B | H72: phone | I72: What can they give — office hours, referrals into Cyera, mentoring? And what do they need from us right now? | J72: +972546611903 | K72: alonwolfy@gmail.com
A73: 46407 | B73: Wed | C73: 19 | D73: Q2 | E73: Ariel Bachar | F73: #3 | G73: B | H73: phone | I73: What can they give — office hours, referrals into Zafran, mentoring? And what do they need from us right now? | J73: +972545301526 | K73: relrelbachar@gmail.com
A74: 46411 | B74: Sun | C74: 20 | D74: Q2 | E74: Meir Adest | F74: #1 | G74: A | H74: linkedin | I74: Node candidate. What can they open for our alumni, and would they give office hours?
A75: 46412 | B75: Mon | C75: 20 | D75: Q2 | E75: Avraham Berrebi | F75: #3 | G75: B | H75: phone | I75: What can they give — office hours, referrals, mentoring? And what do they need from us right now? | J75: +972526207606 | K75: avraham.berr@gmail.com
A76: 46413 | B76: Tue | C76: 20 | D76: Q2 | E76: Adi Tzhori Moshe | F76: #3 | G76: C | H76: linkedin | I76: Stay current — still at Kardome (voice AI)? What are they working on in ai-ml, and what would help?
A77: 46418 | B77: Sun | C77: 21 | D77: Q2 | E77: Michael Kellner | F77: #1 | G77: A | H77: phone | I77: Node candidate — founded SendBlocks. What can they open for our alumni, and would they give office hours? | J77: +972545311213 | K77: mike53il@gmail.com
A78: 46419 | B78: Mon | C78: 21 | D78: Q2 | E78: Uri Shaked | F78: #1 | G78: A | H78: linkedin | I78: Node candidate. What can they open for our alumni, and would they give office hours?
A79: 46420 | B79: Tue | C79: 21 | D79: Q2 | E79: Georgy Melamed | F79: #3 | G79: B | H79: phone | I79: What can they give — office hours, referrals into Walmart Global Tech, mentoring? And what do they need from us right now? | J79: +972523872832 | K79: gmelamed@gmail.com
A80: 46421 | B80: Wed | C80: 21 | D80: Q2 | E80: Adir Kobovich | F80: #3 | G80: C | H80: phone | I80: Stay current — still at Technion (coding/information theory, DNA storage lab)? What are they working on in research, and what would help? | J80: +972546540789 | K80: adir.kob@gmail.com
A81: 46425 | B81: Sun | C81: 22 | D81: Q2 | E81: Zvi Wexlstein | F81: #1 | G81: A | H81: email | I81: Transition point — what are they building or moving toward, what is the blocker, and who should they meet? | K81: zviwex@gmail.com
A82: 46426 | B82: Mon | C82: 22 | D82: Q2 | E82: Almog Zer | F82: #2 | G82: A | H82: phone | I82: Founding track — building this year? What is the blocker, is co-founder the gap, and who should they meet? | J82: +972507363131 | K82: almogx3@gmail.com
A83: 46427 | B83: Tue | C83: 22 | D83: Q2 | E83: Guy Goldenberg | F83: #3 | G83: B | H83: phone | I83: What can they give — office hours, referrals into Wiz, mentoring? And what do they need from us right now? | J83: +972542172153 | K83: guy.goldenberg@gmail.com
A84: 46428 | B84: Wed | C84: 22 | D84: Q2 | E84: Idan Lev-Yehudi | F84: #3 | G84: B | H84: phone | I84: What can they give — office hours, referrals into Technion Autonomous Systems (POMDP planning), mentoring? And what do they need from us right now? | J84: +972523059999 | K84: idanly98@gmail.com
A85: 46432 | B85: Sun | C85: 23 | D85: Q2 | E85: Bar Matityahu | F85: #2 | G85: A | H85: phone | I85: Founding track — building this year? What is the blocker, is co-founder the gap, and who should they meet? | J85: +972525892000 | K85: barmatit@gmail.com
A86: 46433 | B86: Mon | C86: 23 | D86: Q2 | E86: Itamar Gilad | F86: #3 | G86: B | H86: phone | I86: What can they give — office hours, referrals into Wiz, mentoring? And what do they need from us right now? | J86: +972504787314 | K86: itamar.gilad@wiz.io
A87: 46434 | B87: Tue | C87: 23 | D87: Q2 | E87: Itay Gissis | F87: #3 | G87: B | H87: phone | I87: What can they give — office hours, referrals into nT-Tao (compact fusion), mentoring? And what do they need from us right now? | J87: +972504039870 | K87: itaigiss@gmail.com
A88: 46435 | B88: Wed | C88: 23 | D88: Q2 | E88: Amir Balva | F88: #3 | G88: C | H88: phone | I88: Stay current — what are they working on now, and what would help? | J88: +972525591311 | K88: amirbalva@gmail.com
A89: 46439 | B89: Sun | C89: 24 | D89: Q2 | E89: Benny Rousso | F89: #2 | G89: A | H89: phone | I89: Node candidate — founded Xcardia. What can they open for our alumni, and would they give office hours? | J89: +972544345653 | K89: rousso.benny@gmail.com
A90: 46440 | B90: Mon | C90: 24 | D90: Q2 | E90: Liad Ben Uri | F90: #3 | G90: B | H90: phone | I90: What can they give — office hours, referrals into Weizmann (Milo lab, Nature co-author), mentoring? And what do they need from us right now? | J90: +972546326372 | K90: liadgo2@gmail.com
A91: 46441 | B91: Tue | C91: 24 | D91: Q2 | E91: Amitai Nevo | F91: #3 | G91: C | H91: phone | I91: Stay current — still at Franklin by QIAGEN? What are they working on, and what would help? | J91: +972522344098 | K91: amitai.nevo2@gmail.com
A92: 46446 | B92: Sun | C92: 25 | D92: Q2 | E92: Gal Wiernik | F92: #2 | G92: A | H92: phone | I92: Node candidate — founded Edwin. What can they open for our alumni, and would they give office hours? | J92: +972502338655 | K92: galwiernik@gmail.com
A93: 46447 | B93: Mon | C93: 25 | D93: Q3 | E93: Guy Yoshpe | F93: #2 | G93: A | H93: phone | I93: Founding track — building this year? What is the blocker, is co-founder the gap, and who should they meet? | J93: +972508717313 | K93: yoshpe@gmail.com
... A95: 46449 | B95: Wed | C95: 25 | D95: Q3 | E95: Matan Shoef | F95: #3 | G95: B | H95: phone | I95: What can they give — office hours, referrals into OpenEyes, mentoring? And what do they need from us right now? | J95: +972545221060 | K95: matan.shoef@gmail.com
A96: 46453 | B96: Sun | C96: 26 | D96: Q3 | E96: Eldad Kepten | F96: #1 | G96: B | H96: linkedin | I96: What can they give — office hours, referrals, mentoring? And what do they need from us right now?
A97: 46454 | B97: Mon | C97: 26 | D97: Q3 | E97: Hila Shmuel | F97: #2 | G97: A | H97: phone | I97: Node candidate — founded Cabinet (AI workspace). What can they open for our alumni, and would they give office hours? | J97: +972508871171 | K97: hila4321@gmail.com
A98: 46455 | B98: Tue | C98: 26 | D98: Q3 | E98: Iddan Golomb | F98: #2 | G98: A | H98: phone | I98: Node candidate — founded Sayata. What can they open for our alumni, and would they give office hours? | J98: +972542421974 | K98: igolomb@gmail.com
A99: 46456 | B99: Wed | C99: 26 | D99: Q3 | E99: Avichay Radovsky | F99: #3 | G99: C | H99: phone | I99: Roll-up — no verified role on file. What are they doing now, where are they heading, and what do they need? | J99: +972526351833 | K99: avichayr@gmail.com
A100: 46460 | B100: Sun | C100: 27 | D100: Q3 | E100: Eran Hertzmann | F100: #1 | G100: B | H100: phone | I100: What can they give — office hours, referrals, mentoring? And what do they need from us right now? | J100: +972545424895 | K100: eran.hertzmann@gmail.com
A101: 46461 | B101: Mon | C101: 27 | D101: Q3 | E101: Gai Gutherz | F101: #1 | G101: B | H101: linkedin | I101: What can they give — office hours, referrals into Miggo, mentoring? And what do they need from us right now?
A102: 46462 | B102: Tue | C102: 27 | D102: Q3 | E102: Jonathan Gilat | F102: #2 | G102: A | H102: phone | I102: Node candidate — founded Medida AI. What can they open for our alumni, and would they give office hours? | J102: +972528198278 | K102: jonathan@medida.ai
A103: 46463 | B103: Wed | C103: 27 | D103: Q3 | E103: Liran Markin | F103: #2 | G103: A | H103: phone | I103: Node candidate — founded Edwin. What can they open for our alumni, and would they give office hours? | J103: +972544911254 | K103: liran.markin@gmail.com
A104: 46467 | B104: Sun | C104: 28 | D104: Q3 | E104: Michal Shilo | F104: #1 | G104: B | H104: phone | I104: What can they give — office hours, referrals, mentoring? And what do they need from us right now? | J104: +972524598022 | K104: michalshilo6@gmail.com
A105: 46468 | B105: Mon | C105: 28 | D105: Q3 | E105: Nadav Zemach | F105: #1 | G105: B | H105: linkedin | I105: What can they give — office hours, referrals, mentoring? And what do they need from us right now?
A106: 46469 | B106: Tue | C106: 28 | D106: Q3 | E106: Michael Komraz | F106: #2 | G106: A | H106: phone | I106: Founding track — building this year? What is the blocker, is co-founder the gap, and who should they meet? | J106: +972544319975 | K106: mikomraz@gmail.com
...

Sheet Roster
A1: ID | B1: Name | C1: שם בעברית | D1: Cohort | E1: Founder track | F1: Unit | G1: Company | H1: Role | I1: Location | J1: Domain | K1: Tier | L1: Tie strength | M1: Now / current goal | N1: Needs | O1: Can help with | P1: Last contact | Q1: Source | R1: NEXT ACTION | S1: Due | T1: LinkedIn | U1: Email | V1: Phone | W1: Source note (GPU screen, 15/07) | X1: Notes
A2: 6 | B2: Assaf Monsa | D2: #1 | F2: Talpiot | H2: Co-Founder, CTO & VP R&D, D-Fend Solutions | I2: Netanya, Israel | J2: security | K2: A | T2: https://www.linkedin.com/in/assaf-monsa-72a84/ | U2: assafmonsa@gmail.com | V2: +972544319991 | W2: Founded and scaled a real-time RF/hardware company (counter-drone) as CTO/VP R&D - proven physical-systems founder. Domain gap (RF, not GPU/power) and committed to D-Fend. | X2: [dex import] education: תלפיות · tags: Apex Newsletter,Signed To Apex,Fireside Chat,19/10/25 Closing Event,Apex Grad
A3: 1 | B3: Aviel Adler | D3: #1 | H3: R&D | I3: Israel | K3: C | T3: https://www.linkedin.com/in/aviel-a-a87b2612/ | U3: avieladler@gmail.com | V3: +972549954666 | W3: No company/role data in roster and no reliable public technical record found against the criteria (GPU systems, power, real-time control). | X3: [dex import] education: תלפיות · tags: Apex Newsletter,Signed To Apex,Fireside Chat,Apex Grad
A4: 9 | B4: Daniel Ohayon | D4: #1 | F4: Psagot | H4: MSc student, Technion | I4: Jerusalem District, Israel | J4: research | K4: C | T4: https://www.linkedin.com/in/daniel-ohayon-45b68513a | V4: +972524056440 | W4: Graduate student, Psagot. Insufficient production record to score above the average band.
A5: 8 | B5: Danny Grander | D5: #1 | F5: ARAM | G5: Snyk | H5: Co-Founder | I5: Israel | J5: security | K5: A | T5: https://www.linkedin.com/in/grander | U5: danny.grander@gmail.com | V5: +972507616594 | W5: World-class 0-to-1 founder signal (Snyk) and now angel - but zero domain overlap with GPU/power. Not an operator fit; top-tier angel/advisor target for Joulix's next round. | X5: [dex import] met with: Can help Apex · education: ארם · tags: Apex Donor,PEF,Apex Newsletter,Mega Connector,Signed To Apex,Fireside Chat,Coffee Avishag,19/10/25 Closing Event,25/2/2026 - Closing Event,Apex Grad
A6: 10 | B6: Dror Ben Eliezer | D6: #1 | F6: Talpiot | H6: Independent Consultant, ex-Nike | J6: product-gtm | K6: C | T6: https://www.linkedin.com/in/dror-ben-eliezer-b084406/ | W6: Consulting profile, no evidence of hands-on systems/infra work relevant to the criteria.
A7: 5 | B7: Eldad Kepten | D7: #1 | F7: Talpiot | H7: Leading Data Scientist (research-to-product) | J7: ai-ml | K7: B | T7: https://www.linkedin.com/in/eldad-kepten-441ba124/ | W7: Senior data scientist bridging research to product. Relevant analytical horsepower, no systems/power/GPU evidence.
A8: 20 | B8: Eran Hertzmann | D8: #1 | F8: Talpiot | H8: Product Executive, AI digital health | I8: Tel-Aviv District, Israel | J8: ai-ml | K8: B | T8: https://www.linkedin.com/in/eran-hertzmann-24a400 | U8: eran.hertzmann@gmail.com | V8: +972545424895 | W8: Product executive, health tech. Not a technical founding fit for this domain. | X8: [dex import] education: תלפיות · tags: Apex Newsletter,Signed To Apex,Fireside Chat,Apex Grad
A9: 19 | B9: Eran Hirsch | D9: #1 | F9: ARAM | H9: Freelance Full-Stack, ex-Meta | I9: Givatayim, Tel-Aviv District, Israel | J9: infra-systems | K9: C | T9: https://www.linkedin.com/in/eranhirsch | U9: eranhirsch@gmail.com | V9: +972548303525 | W9: Ex-Meta full-stack freelancer. Application layer; no systems/power depth in public record. | X9: [dex import] education: אר"ם · tags: Apex Newsletter,Signed To Apex,Fireside Chat,19/10/25 Closing Event,Apex Grad
A10: 4 | B10: Eyal Kraft | D10: #1 | F10: ARAM | G10: Stealth | H10: CTO | K10: A | T10: https://www.linkedin.com/in/eyalkraft | W10: CTO of a stealth company - cannot assess technical fit without knowing the domain, and availability is presumptively zero. Track, don't pitch.
A11: 7 | B11: Gai Gutherz | D11: #1 | F11: Talpiot | G11: Miggo | H11: Head of Technical Product | J11: security | K11: B | T11: https://www.linkedin.com/in/gai-gutherz | W11: Technical product leadership in appsec. No systems/power/GPU record.
A12: 18 | B12: Inbal Beracha | D12: #1 | F12: Talpiot | G12: Stealth | H12: Founding Engineer | K12: A | T12: https://www.linkedin.com/in/inbal-beracha-a668ab182/ | W12: Founding engineer at stealth - domain unknown, availability presumptively zero.
A13: 11 | B13: Meir Adest | D13: #1 | F13: Talpiot | H13: Co-Founder, SolarEdge Technologies | J13: hardware-embedded | K13: A | T13: https://www.linkedin.com/in/meiradest/ | W13: Co-founded SolarEdge - the defining company in power-optimization electronics (per-panel DC optimization, i.e. 'maximize output per installed watt'), scaled to a global public company. Exact business logic of Joulix in a different asset class. Won't join as operator; exceptional as founding chairman / technical advisor / seed investor.
A14: 12 | B14: Michael Kellner | D14: #1 | F14: Talpiot | G14: SendBlocks | H14: Co-Founder & CTO | K14: A | T14: https://www.linkedin.com/in/michael-kellner-689258206 | U14: mike53il@gmail.com | V14: +972545311213 | W14: Infra founder-CTO (blockchain data infrastructure). Real infra chops, committed elsewhere, no power/GPU record. | X14: [dex import] education: תלפיות · tags: Apex Newsletter,Signed To Apex,Fireside Chat,25/2/2026 - Closing Event,Apex Grad
A15: 13 | B15: Michal Shilo | D15: #1 | F15: Talpiot | H15: Data Scientist | I15: Tel Aviv-Yafo, Tel Aviv District, Israel | J15: ai-ml | K15: B | T15: https://www.linkedin.com/in/michal-shilo-ba3002190/ | U15: michalshilo6@gmail.com | V15: +972524598022 | W15: Data scientist, Talpiot. No systems/power/GPU evidence. | X15: [dex import] education: תלפיות · tags: Apex Newsletter,Signed To Apex,Fireside Chat,Apex Grad
A16: 14 | B16: Nadav Zemach | D16: #1 | F16: Talpiot | H16: Director Advisor, Ministry of Finance | J16: product-gtm | K16: B | T16: https://www.linkedin.com/in/nadav-zemach-477a42365/ | W16: Government finance advisor - not a technical fit for a founding team. Separately valuable for sovereign-AI / regulatory / grant angles.
A17: 16 | B17: Nir Yaron | D17: #1 | F17: Talpiot | H17: Unknown | K17: C | T17: https://www.linkedin.com/in/nir-yaron-886051241 | W17: No role data in roster/alumni page and no reliable public technical record found.
A18: 15 | B18: Noy Duany | D18: #1 | F18: ARAM | G18: Hopper Security | H18: R&D Team Lead | J18: security | K18: B | T18: https://www.linkedin.com/in/noyduany/ | W18: Cyber R&D team lead. Solid engineer-leader, wrong domain.
A19: 2 | B19: Ohad Amosy | D19: #1 | F19: Talpiot | H19: AI-COE / ML researcher (Bar-Ilan, Chechik lab) | J19: research | K19: B | T19: https://il.linkedin.com/in/ohad-amosy | W19: Published ML researcher (WACV, EMNLP; federated learning, hypernetworks) incl. a neural-network-driven QAOA optimization paper and co-authorship with NVIDIA Research-affiliated lab. Strong optimization/ML brain for the control-policy side; no GPU systems or power production record.
A20: 17 | B20: Omer Hay | D20: #1 | F20: Psagot | H20: Software Engineer / R&D Team Lead | I20: Israel | J20: infra-systems | K20: B | T20: https://www.linkedin.com/in/hay-omer | W20: Generalist SWE/team lead. No domain evidence.
A21: 24 | B21: Rami Anati | D21: #1 | F21: Talpiot | H21: Team Lead / Back-End Project Manager | J21: infra-systems | K21: B | T21: https://www.linkedin.com/in/ramianati | W21: Backend team lead/PM. No domain evidence.
A22: 23 | B22: Roee Yaron | D22: #1 | F22: Talpiot | G22: Ministry of Defense | H22: Physicist | J22: quantum-physics | K22: B | W22: Defense physicist, Talpiot. Hard-science depth, no software-infrastructure record.
A23: 22 | B23: Ronen Tur | D23: #1 | F23: Talpiot | H23: Director of Algorithms & Deep Learning | J23: ai-ml | K23: B | T23: https://www.linkedin.com/in/ronen-tur-641a0a18/ | W23: Senior algorithms/DL leadership - relevant to the optimization brain of a power-control loop, but no public GPU/power specifics.
A24: 25 | B24: Shachar Cohen | D24: #1 | F24: Talpiot | H24: Software R&D Engineer & Manager | J24: product-gtm | K24: B | T24: https://www.linkedin.com/in/shachar-cohen-480b86205 | W24: SW R&D engineer/manager, Talpiot. No domain evidence.
A25: 26 | B25: Shai Elroy | D25: #1 | F25: Psagot | H25: R&D Team Lead, Cyber | J25: security | K25: B | T25: https://www.linkedin.com/in/shai-elroy | W25: Cyber R&D team lead. Wrong domain.
A26: 3 | B26: Uri Shaked | D26: #1 | F26: ARAM / Founder | H26: Founder, Wokwi + TinyTapeout | J26: hardware-embedded | K26: A | T26: https://www.linkedin.com/in/urishaked/ | W26: Built Wokwi (embedded/silicon simulation) and active in open silicon (TinyTapeout) - rare HW/SW boundary depth, exactly the instinct a firmware-adjacent power layer needs. No GPU DVFS/data-center record; committed to his own products. Best used as technical advisor.
A27: 21 | B27: Zvi Wexlstein | D27: #1 | E27: yes | F27: ARAM | H27: Software Architect, Polar (IBM) | J27: infra-systems | K27: A | T27: https://www.linkedin.com/in/zvi-wexlstein | U27: zviwex@gmail.com | W27: Software architect at Polar/IBM; Founder Track signal. Solid architect, no power/GPU record. | X27: [dex import] tags: Fireside Chat
A28: 30 | B28: Almog Zer | D28: #2 | F28: Psagot | G28: Stealth | H28: R&D Group Lead | I28: Israel | K28: A | T28: https://www.linkedin.com/in/almog-zer-865897118 | U28: almogx3@gmail.com | V28: +972507363131 | W28: Group lead at stealth - domain unknown, availability low. | X28: [dex import] military course: טו · met with: Can help Apex · warm intro via: Lutati · education: פסגות · tags: Fireside Chat,Signed To Apex,Apex Newsletter,Watchlist,25/2/2026 - Closing Event,Apex Grad
A29: 27 | B29: Aviel Zecharia | D29: #2 | F29: ARAM | G29: Palo Alto Networks | H29: Architect | I29: Rishon LeZion, Israel | J29: security | K29: B | T29: https://www.linkedin.com/in/aviel-zecharia-832a66131/ | U29: avielz1199@gmail.com | V29: +972547260058 | W29: Security architect at PAN. Strong engineer, security domain. | X29: [dex import] military course: 20 · education: אר"ם · tags: 25/2/2026 - Closing Event,Fireside Chat,Apex Newsletter,Signed To Apex,Architect Cohort #2,Apex Grad
A30: 33 | B30: Bar Matityahu | D30: #2 | F30: Psagot | G30: Stealth | H30: Founder | I30: Tel-Aviv District, Israel | K30: A | T30: https://www.linkedin.com/in/bar-matityahu | U30: barmatit@gmail.com | V30: +972525892000 | W30: Stealth founder - unknowable and unavailable. | X30: [dex import] military course: מחזור י - חשמל פיזיקה טכניון · education: פסגות · tags: 25/2/2026 - Closing Event,Fireside Chat,Apex Newsletter,Signed To Apex,Architect Cohort #2,Apex Grad
A31: 32 | B31: Benny Rousso | D31: #2 | F31: Talpiot | G31: Xcardia | H31: CEO & Founder | I31: Tel Aviv, Tel-Aviv District, Israel | J31: health-bio | K31: A | T31: http://linkedin.com/in/benny-rousso-27832b32b | U31: rousso.benny@gmail.com | V31: +972544345653 | W31: Founder-CEO in medical imaging. Founder DNA, wrong domain, committed. | X31: [dex import] military course: 9 · education: תלפיות · tags: 25/2/2026 - Closing Event,Fireside Chat,Apex Newsletter,Signed To Apex,Architect Cohort #2,Apex Grad
A32: 31 | B32: Benzion Kossowsky | D32: #2 | F32: ARAM | H32: OneStep | I32: West Jerusalem, Jerusalem District, Israel | K32: C | T32: https://www.linkedin.com/in/benzionkossowsky | U32: benzionkossowsky@gmail.com | V32: +972543315821 | W32: At OneStep (digital health/motion analysis). No domain evidence. | X32: [dex import] military course: 22 · education: אר״מ · tags: Fireside Chat,Apex Newsletter,Signed To Apex,25/2/2026 - Closing Event,Architect Cohort #2,Apex Grad
A33: 28 | B33: Eyal Horowicz | D33: #2 | F33: Talpiot | G33: Claroty (DS Team Leader per roster) | H33: Senior SWE | I33: Tel-Aviv District, Israel | J33: security | K33: B | T33: https://www.linkedin.com/in/eyal-horowicz | U33: eyalhoro6@gmail.com | V33: +972506228892 | W33: Senior engineer at Claroty (OT/ICS security) - adjacent to industrial control environments, but security-side, not performance/power. | X33: [dex import] military course: 36 · education: תלפיות · tags: Fireside Chat,Apex Newsletter,Signed To Apex,25/2/2026 - Closing Event,Architect Cohort #2,Apex Grad
A34: 36 | B34: Gal Wiernik | D34: #2 | F34: Arazim | G34: Edwin | H34: CTO | I34: Tel Aviv, Tel-Aviv District, Israel | J34: ai-ml | K34: A | T34: https://www.linkedin.com/in/galwiernik | U34: galwiernik@gmail.com | V34: +972502338655 | W34: Genuine HPC pedigree: co-author of an IPDPS 2024 paper on fast, stable matrix multiplication - performance engineering of the exact kernels GPUs burn watts on - plus AI-infra experience and TAU research excellence awards. Now CTO at Edwin, so likely unavailable; skills-wise the top available-market operator in the roster. | X34: [dex import] military course: ארזים ט׳ · met with: NA · education: ארזים · tags: Apex Newsletter,Signed To Apex,25/2/2026 - Closing Event,Architect Cohort #2,Fireside Chat,Apex Grad
A35: 35 | B35: Gil Raytan | D35: #2 | F35: Psagot | G35: Remitly (AI/ML) | H35: Director of Engineering | I35: Israel | J35: ai-ml | K35: B | T35: https://www.linkedin.com/in/gil-raytan/ | U35: gil.raytan@gmail.com | V35: +972544322242 | W35: Eng leadership over AI/ML at fintech scale. VP-Eng-later-stage profile, not founding GPU-systems fit. | X35: [dex import] military course: ט · education: פסגות · tags: 25/2/2026 - Closing Event,Fireside Chat,Apex Newsletter,Signed To Apex,Architect Cohort #2,Apex Grad
A36: 34 | B36: Guy Yoshpe | D36: #2 | F36: ARAM | G36: Wiz | H36: Building | I36: Israel | J36: security | K36: A | T36: https://www.linkedin.com/in/yoshpe | U36: yoshpe@gmail.com | V36: +972508717313 | W36: Proven founder-CTO now at Wiz. Elite cloud engineering environment; application/cloud layer rather than GPU/power systems.
A37: 37 | B37: Hila Shmuel | D37: #2 | F37: ARAM | G37: Cabinet (AI workspace) | H37: Co-Founder | I37: Tel-Aviv District, Israel | J37: ai-ml | K37: A | T37: https://www.linkedin.com/in/hilashmuel/ | U37: hila4321@gmail.com | V37: +972508871171 | W37: AI-product founder. Founder DNA, committed, different layer of the stack. | X37: [dex import] military course: יב · met with: Raised · education: אר״מ · tags: Fireside Chat,Apex Newsletter,Signed To Apex,25/2/2026 - Closing Event,Apex Grad
A38: 51 | B38: Iddan Golomb | D38: #2 | F38: Talpiot | G38: Sayata | H38: Co-Founder & CPO | I38: Israel | J38: product-gtm | K38: A | T38: https://www.linkedin.com/in/iddangolomb/ | U38: igolomb@gmail.com | V38: +972542421974 | W38: Product co-founder. Founder DNA, committed, product-side. | X38: [dex import] military course: 25 · education: תלפיות · tags: 25/2/2026 - Closing Event,Fireside Chat,Apex Newsletter,Signed To Apex,Architect Cohort #2,Apex Grad
A39: 50 | B39: Ido Kazma | D39: #2 | F39: Talpiot | G39: Q.ai | H39: Algo Team Lead | I39: Israel | J39: ai-ml | K39: B | T39: https://www.linkedin.com/in/idokazma | U39: idokazma@gmail.com | V39: +972528584131 | W39: Algorithms team lead. Relevant optimization skills, no systems/power record. | X39: [dex import] military course: 31 · education: תלפיות · tags: 25/2/2026 - Closing Event,Fireside Chat,Apex Newsletter,Signed To Apex,Architect Cohort #2,Apex Grad
A40: 29 | B40: Ilan Voronel | D40: #2 | F40: Talpiot | G40: Glassbox | H40: ML & DS Team Leader | I40: Israel | J40: ai-ml | K40: B | T40: https://www.linkedin.com/in/ilan-voronel/ | U40: ilan.voronel@gmail.com | V40: +972547397052 | W40: ML/DS team leadership. No systems/power record. | X40: [dex import] military course: 24 · education: תלפיות · tags: Fireside Chat,Apex Newsletter,Signed To Apex,25/2/2026 - Closing Event,Architect Cohort #2,Apex Grad
A41: 38 | B41: Jonathan Gilat | D41: #2 | F41: Talpiot | G41: Medida AI | H41: Co-Founder | I41: Tel Aviv, Tel-Aviv District, Israel | J41: ai-ml | K41: A | T41: https://www.linkedin.com/in/jonathangilat | U41: jonathan@medida.ai | V41: +972528198278 | W41: Talpiot + 8200 co-founder. Committed to Medida; domain (health AI) different. | X41: [dex import] military course: 37 · met with: Keep in touch · education: תלפיות · tags: Fireside Chat,Apex Newsletter,Signed To Apex,25/2/2026 - Closing Event,Architect Cohort #2,Apex Grad
A42: 41 | B42: Kfir Shoar | D42: #2 | F42: Talpiot | G42: Cyera | H42: Software Developer | J42: security | K42: C | W42: SWE at Cyera. No domain evidence.
A43: 42 | B43: Lior Lev Tov | D43: #2 | F43: ARAM | G43: Eon.io | H43: Software Engineer | I43: Tel-Aviv District, Israel | J43: infra-systems | K43: C | T43: https://www.linkedin.com/in/liorlevtov | U43: liorlevtov@gmail.com | V43: +972542267010 | W43: SWE at cloud backup startup. No domain evidence. | X43: [dex import] military course: ח · met with: Keep in touch · education: אר״מ · tags: 25/2/2026 - Closing Event,Fireside Chat,Apex Newsletter,Signed To Apex,Mega Connector,Avishag's Substack,Apex Grad
A44: 43 | B44: Liran Markin | D44: #2 | F44: ARAM | G44: Edwin | H44: CEO | I44: Tel-Aviv District, Israel | K44: A | T44: https://www.linkedin.com/in/liran-markin/ | U44: liran.markin@gmail.com | V44: +972544911254 | W44: Founder-CEO (with Gal Wiernik as CTO). Founder DNA; committed to Edwin. | X44: [dex import] military course: קורס י״ט · met with: NA · education: אר״מ · tags: Fireside Chat,Apex Newsletter,Signed To Apex,25/2/2026 - Closing Event,Apex Grad
A45: 46 | B45: Michael Komraz | D45: #2 | F45: ARAM | H45: Building something new; ex-Snyk CTO Office | J45: security | K45: A | T45: https://www.linkedin.com/in/michael-komraz/ | U45: mikomraz@gmail.com | V45: +972544319975 | W45: Ex-Snyk CTO office, currently in founder mode. Strong generalist; committed to own thing.
A46: 45 | B46: Michael Zuzovski | D46: #2 | F46: Psagot | G46: TAU (ex-Amazon) | H46: Researcher | J46: research | K46: B | T46: https://www.linkedin.com/in/michael-z-2355655a | U46: giga123@gmail.com | V46: +972527564010 | W46: Ex-Amazon, now academic researcher. No power/GPU record.
A47: 47 | B47: Michal Ran Shchory | D47: #2 | F47: Psagot | G47: Protai | H47: SW & Algorithms | I47: Tel-Aviv District, Israel | J47: ai-ml | K47: C | T47: https://www.linkedin.com/in/michal-ran | U47: michalran95@gmail.com | V47: +972544443440 | W47: Algo engineer in bio/proteomics AI. No domain evidence. | X47: [dex import] military course: ט״ו · education: פסגות · tags: 25/2/2026 - Closing Event,Fireside Chat,Apex Newsletter,Signed To Apex,Apex Grad
A48: 44 | B48: Mor Shemesh | D48: #2 | F48: ARAM | G48: Stealth | H48: Founding Engineer | I48: Israel | K48: A | T48: https://www.linkedin.com/in/mor-shemesh-1bb04a155 | U48: mor.m.shemesh@gmail.com | V48: +972507711998 | W48: Stealth founding engineer - unknowable, unavailable.
A49: 48 | B49: Omer Onn | D49: #2 | F49: Psagot | G49: Akeyless (ex-System Architect, DriveNets) | H49: Cloud & Tech Alliance Mgr | I49: Israel | J49: security | K49: B | T49: https://www.linkedin.com/in/omer-onn-0b980961 | U49: omeronn@gmail.com | V49: +972508112332 | W49: Real systems depth from DriveNets (carrier-scale networking), but has pivoted to BD/alliances. Better fit for a partnerships role than founding engineering. | X49: [dex import] military course: ו · education: פסגות · tags: 25/2/2026 - Closing Event,Fireside Chat,Apex Newsletter,Signed To Apex,Apex Grad
A50: 49 | B50: Omri Gotlib | D50: #2 | F50: ARAM | H50: Team Lead, Security Research | I50: Tel Aviv, Tel-Aviv District, Israel | J50: security | K50: B | T50: https://www.linkedin.com/in/omri-gotlib-223288260/ | U50: gotlib.omri@gmail.com | V50: +972528225572 | W50: Security research lead. Wrong domain. | X50: [dex import] military course: כ · education: אר״מ · tags: 25/2/2026 - Closing Event,Fireside Chat,Apex Newsletter,Signed To Apex,Apex Grad
A51: 52 | B51: Peleg Ben Hamo | D51: #2 | F51: Talpiot | G51: Cyera | H51: Software Developer | I51: Tel Aviv, Tel-Aviv District, Israel | J51: security | K51: C | T51: https://www.linkedin.com/in/peleg-ben-hamo-a90034355 | U51: peleg87@gmail.com | V51: +972524447878 | W51: SWE at Cyera. No domain evidence. | X51: [dex import] military course: 36 · education: תלפיות · tags: 25/2/2026 - Closing Event,Fireside Chat,Apex Newsletter,Signed To Apex,Apex Grad
A52: 54 | B52: Ron Galay | D52: #2 | F52: Psagot | G52: Datadog | H52: Senior SWE | I52: Israel | J52: infra-systems | K52: B | T52: https://www.linkedin.com/in/ron-galay-0b451662 | U52: rongalay@gmail.com | V52: +972503039885 | W52: Senior SWE at Datadog - large-scale observability is mildly adjacent (telemetry pipelines), but no power/GPU record. | X52: [dex import] military course: ט · education: פסגות · tags: Fireside Chat,Apex Newsletter,Signed To Apex,25/2/2026 - Closing Event,Apex Grad
A53: 55 | B53: Roy Moshe | D53: #2 | E53: yes | F53: Psagot | G53: Stealth | H53: CEO | I53: Givatayim, Tel Aviv District, Israel | K53: A | T53: https://www.linkedin.com/in/roy-moshe-0727b115b | U53: roymoshe23@gmail.com | V53: +972546777815 | W53: Stealth CEO, Founder Track. Unknowable and unavailable; track what he's building. | X53: [dex import] military course: ט״ו · unit: Psagot · domains: Agentic AI Workflow · role tag: CEO · commitment: 2 - רמה בינונית · tags: Apex Inception May 2026
A54: 56 | B54: Shachar Resisi | D54: #2 | F54: Egoz | G54: Vayyar Imaging | H54: Algorithm Developer | I54: Tel Aviv-Yafo, Tel Aviv District, Israel | J54: ai-ml | K54: C | T54: https://www.linkedin.com/in/shachar-resisi | U54: shachar.resisi@gmail.com | V54: +972542566787 | W54: Algorithms at an RF-imaging chip company - hardware-adjacent algo work. | X54: [dex import] military course: א · education: אגוז (לא של גולני) · tags: 25/2/2026 - Closing Event,Fireside Chat,Apex Newsletter,Signed To Apex,Apex Grad
A55: 57 | B55: Shaked Yehezkel | D55: #2 | F55: ARAM | G55: TAU | H55: Researcher | J55: research | K55: B | W55: Academic researcher. Insufficient record.
A56: 58 | B56: Sharon Brizinov | D56: #2 | F56: Saylan | H56: Security Researcher (ICS/OT, firmware) | I56: Israel | J56: security | K56: B | T56: https://www.linkedin.com/in/sharonbrizinov/ | U56: sharon.brizinov@gmail.com | V56: +972544702148 | W56: Elite low-level/firmware vulnerability researcher in the ICS/OT world. Reverse-engineering and firmware depth transfer directly to a layer sitting near GPU firmware/drivers - but it's security, not performance/power, and no infra-scaling record. | X56: [dex import] military course: ט · met with: Keep in touch · education: סילאן · tags: 25/2/2026 - Closing Event,Fireside Chat,Apex Newsletter,Signed To Apex,Apex Grad
A57: 59 | B57: Tomer Goren | D57: #2 | F57: Talpiot | H57: 'Building' (per APEX alumni page) | K57: A | T57: https://www.linkedin.com/in/אין | U57: tomergoren99@gmail.com | V57: +972544744575 | W57: In founder mode, domain unknown. Cannot assess. | X57: [dex import] military course: 39 · tags: Fireside Chat,Apex Newsletter
A58: 53 | B58: Tzah Pahima | D58: #2 | F58: ARAM | G58: Orca Security | H58: Cloud Security Researcher | I58: Ramat Gan, Tel-Aviv District, Israel | J58: security | K58: B | T58: https://www.linkedin.com/in/tzah-pahima-6b5b75178 | U58: tzahpahima123@gmail.com | V58: +972538271198 | W58: Cloud security researcher. Deep cloud internals knowledge, security-side. | X58: [dex import] military course: ט׳ · education: אר״מ · tags: 25/2/2026 - Closing Event,Fireside Chat,Apex Newsletter,Signed To Apex,Apex Grad
A59: 40 | B59: Yakov Kosoburd | D59: #2 | F59: Talpiot | H59: MSc Research Student, Weizmann | I59: Tel Aviv, Tel-Aviv District, Israel | J59: research | K59: B | T59: https://www.linkedin.com/in/yakov-kosoburd-8b8aa127a | U59: yakov.kosoburd@gmail.com | V59: +972529508555 | W59: Graduate researcher. Insufficient production record. | X59: [dex import] military course: 38 · education: תלפיות · tags: Fireside Chat,Apex Newsletter,Signed To Apex,25/2/2026 - Closing Event,Apex Grad
A60: 39 | B60: Yuri Shapira | D60: #2 | F60: ARAM | G60: PureSec (Architect @ PAN per roster) | H60: Principal Researcher | I60: Israel | J60: security | K60: B | T60: https://www.linkedin.com/in/yurishapira | U60: yurishapira@gmail.com | V60: +972547225688 | W60: Principal security researcher/architect. Deep technical, wrong domain. | X60: [dex import] military course: 2003 · education: אחראי מחשוב · tags: 25/2/2026 - Closing Event,Fireside Chat,Apex Newsletter,Signed To Apex,Apex Grad
A61: 92 | B61: Adi Cohen | D61: #3 | H61: Unknown | K61: C | U61: cohenadi02@gmail.com | V61: +972543990302 | W61: Name too common for reliable public disambiguation; no LinkedIn in roster.
A62: 93 | B62: Adi Tzhori Moshe | D62: #3 | G62: Kardome (voice AI) | H62: Embedded Software Developer | J62: ai-ml | K62: C | T62: https://www.linkedin.com/in/adi-tzhori | W62: Embedded SW developer at a voice-AI/DSP startup, ex-Elbit, Technion computer engineering. Embedded/DSP is a relevant profile shape at junior level; no GPU/power record. | X62: [dex import] tags: Architect Cohort #3,30/6/2026 - State of AI
A63: 62 | B63: Adir Kobovich | D63: #3 | G63: Technion (coding/information theory, DNA storage lab) | H63: MSc | I63: Israel | J63: research | K63: C | T63: https://www.linkedin.com/in/adir-kobovich-004494233 | U63: adir.kob@gmail.com | V63: +972546540789 | W63: Coding-theory researcher (arXiv/IEEE publications) with visible bare-metal/embedded interest. Strong theory, junior, no production systems record yet.
A64: 68 | B64: Alon Wolf | D64: #3 | F64: Talpiot (likely) | G64: Cyera | H64: Likely: AI Security Solution Architect | I64: Israel | J64: security | K64: B | T64: https://www.linkedin.com/in/alon-wolf | U64: alonwolfy@gmail.com | V64: +972546611903 | W64: Best identity match: Cyera AI security architect, previously AI research at Decart (a company famous for extreme GPU-efficiency engineering), Talpiot, HUJI BSc + TAU MSc. Decart exposure is a real signal for GPU-efficiency thinking. Identity needs verification (common name incl. a Technion robotics professor).
A65: 69 | B65: Amir Balva | D65: #3 | H65: Cyber Security Leader | I65: Israel | K65: C | T65: https://www.linkedin.com/in/amirbalva | U65: amirbalva@gmail.com | V65: +972525591311 | W65: Web search returned no reliable public technical record for this name.
A66: 70 | B66: Amitai Nevo | D66: #3 | G66: Franklin by QIAGEN | H66: Data Scientist | Impact | Talpiot Alumnus | I66: Israel | K66: C | T66: https://www.linkedin.com/in/amitai-nevo | U66: amitai.nevo2@gmail.com | V66: +972522344098 | W66: Web search returned no reliable public disambiguation for this name.
A67: 71 | B67: Ariel Bachar | D67: #3 | F67: ARAM (roster) | G67: Zafran | H67: Senior Software Engineer | J67: security | K67: B | T67: https://linkedin.com/in/ariel-bachar | U67: relrelbachar@gmail.com | V67: +972545301526 | W67: Senior SWE at Zafran (threat exposure mgmt), ex-military-intelligence security researcher. Solid cyber engineer, wrong domain.
A68: 60 | B68: Avichay Radovsky | D68: #3 | H68: Unknown | K68: C | U68: avichayr@gmail.com | V68: +972526351833 | W68: Web search returned no reliable public technical record for this name.
A69: 61 | B69: Avraham Berrebi | D69: #3 | H69: Quantum Tech Projects Officer, MoD; ex-Rafael; HUJI/Weizmann quantum physics | I69: Israel | J69: research | K69: B | T69: https://il.linkedin.com/in/avraham-berrebi-0981b5266 | U69: avraham.berr@gmail.com | V69: +972526207606 | W69: Quantum-technology program leader at MoD, ex-Rafael researcher, PRL-published quantum physics (spin decoherence). Deep hard-tech + program leadership; no GPU/power-software fit.
A70: 72 | B70: Benny Getz | D70: #3 | F70: Talpiot | G70: Predicta Med | H70: Co-Founder & CTO | I70: Ramat HaSharon, Tel Aviv District, Israel | J70: infra-systems | K70: A | T70: https://www.linkedin.com/in/benny-benjamin-g-93922b | U70: benny.getz@gmail.com | V70: +972545551000 | W70: 25 years of silicon/system architecture: Intel wireless chief-architect roles, Samsung IoT senior director, DSP/signal processing, Talpiot. Deep chip-and-systems architecture DNA - relevant to hardware-aware software - but currently CTO of his own health-AI startup and very senior.
A71: 75 | B71: David Shasha | D71: #3 | G71: Stealth | H71: System Architecture Leader | From Ambiguity to Execution | I71: Tel Aviv District, Israel | K71: C | T71: https://www.linkedin.com/in/shasha-david | U71: davidroyshasha@gmail.com | V71: +972544961009 | W71: Web search returned no reliable public disambiguation for this name.
A72: 76 | B72: Dolev Elbaz | D72: #3 | F72: Psagot | G72: Breeze Security | H72: Co-Founder & CTO | I72: Tel Aviv District, Israel | J72: security | K72: A | T72: https://www.linkedin.com/in/dolevelbaz/ | U72: dolevelb@gmail.com | V72: +972525677675 | W72: One of the strongest systems profiles in the roster: built DDoS-protection datapath for Azure's edge in DPDK + Rust as tech lead ('high performance at scale'), embedded Linux + x86 virtualization background, Israel-Defense-Prize-winning projects, Psagot. Exactly the kernel/datapath engineering Joulix needs - but he is co-founder/CTO of his own funded startup, so availability is ~0. Track closely.
A73: 73 | B73: Georgy Melamed | D73: #3 | G73: Walmart Global Tech | H73: Principal Scientist | I73: Israel | K73: B | T73: https://www.linkedin.com/in/georgy-melamed-0315a71 | U73: gmelamed@gmail.com | V73: +972523872832 | W73: Principal applied scientist (machine vision), ex-Amazon, ex-PrimeSense. Strong applied AI; no power/GPU-systems record.
A74: 74 | B74: Guy Goldenberg | D74: #3 | G74: Wiz | H74: Senior SWE / Security Researcher | I74: Tel Aviv District, Israel | J74: security | K74: B | T74: https://www.linkedin.com/in/guy-goldenberg | U74: guy.goldenberg@gmail.com | V74: +972542172153 | W74: Senior engineer on Wiz's ASM product line; published vulnerability research. Elite cyber engineering, wrong domain.
A75: 77 | B75: Hillel Twersky | D75: #3 | G75: Carefam (AI healthcare hiring, $10.5M raised) | I75: Tel Aviv District, Israel | J75: ai-ml | K75: C | T75: https://www.linkedin.com/in/hillel-twersky | U75: hilleltwersky@gmail.com | V75: +972545258759 | W75: At a funded AI-hiring startup; specific role and technical record not publicly verifiable against the criteria.
A76: 96 | B76: Idan Lev-Yehudi | D76: #3 | F76: Talpiot | G76: Technion Autonomous Systems (POMDP planning) | H76: PhD | I76: Tel Aviv-Yafo, Tel Aviv District, Israel | J76: research | K76: B | T76: https://il.linkedin.com/in/idan-lev-yehudi | U76: idanly98@gmail.com | V76: +972523059999 | W76: Talpiot, ex-Google, publishes at AAAI/RA-L on real-time planning under uncertainty with formal guarantees, where computational cost of models is the core constraint - the intellectual core of Joulix's control loop (decide fast, under uncertainty, with guarantees). No GPU-systems production record; would need a systems counterpart. Best pure 'founding algorithms engineer' bet in cohort #3.
A77: 95 | B77: Ido Ben Tsion | D77: #3 | G77: Toga Networks-a Huawei Company | H77: AI Systems Engineer | GPU/NPU Performance, LLM Fine-Tuning, AI-Assisted Development | I77: Israel | K77: C | T77: https://www.linkedin.com/in/ibentsion | U77: ibentsion@gmail.com | V77: +972523322722 | W77: Web search returned no reliable public disambiguation for this name.
A78: 65 | B78: Ilan Godik | D78: #3 | H78: Research Assistant at The Open University of Israel | I78: Israel | K78: C | T78: https://il.linkedin.com/in/ilan-godik-20a47464 | U78: ilan3580@gmail.com | V78: +972503028929 | W78: Public footprint shows serious functional-programming/type-theory/low-level inclination (active OSS, x86/Haskell/Scala work) - the profile shape of a great kernel engineer - but no verifiable GPU, power, or production-systems record against the criteria. Worth a screening call.
A79: 67 | B79: Itamar Gilad | D79: #3 | G79: Wiz | H79: Threat Detection Lead | I79: Israel | J79: security | K79: B | T79: https://www.linkedin.com/in/igilad/ | U79: itamar.gilad@wiz.io | V79: +972504787314 | W79: Threat-detection lead at Wiz, ex-Microsoft architecture & security lead for large-scale data services. Elite security engineering; no power/GPU/performance record.
A80: 66 | B80: Itay Gissis | D80: #3 | F80: Psagot | G80: nT-Tao (compact fusion) | H80: VP R&D | I80: Center District, Israel | J80: research | K80: B | T80: https://www.linkedin.com/in/itay-gissis/ | U80: itaigiss@gmail.com | V80: +972504039870 | W80: VP R&D at a fusion-energy startup pitching power for the data-hungry world; Technion PhD in pulsed power/plasma. Deep energy-domain physics + multidisciplinary R&D leadership. Not GPU software; committed to nT-Tao. Excellent energy-domain advisor.
A81: 81 | B81: Itzhak Bernstein | D81: #3 | H81: Tech Executive Bridging Deep-Tech and Software at Scale | Cyber, Data & AI, RF | System Architecture & Engineering Leadership | Project Execution | TALPIOT | 8200 | Unit 81 | I81: Tel Aviv-Yafo, Tel Aviv District, Israel | K81: C | T81: https://www.linkedin.com/in/itzhak-bernstein-606808153 | U81: yitzhokt2@gmail.com | V81: +972529280436 | W81: Web search returned no reliable public technical record for this profile.
A82: 82 | B82: Liad Ben Uri | D82: #3 | F82: Talpiot | G82: Weizmann (Milo lab, Nature co-author) | H82: PhD | I82: Haifa, Haifa District, Israel | J82: research | K82: B | T82: https://www.linkedin.com/in/liad-ben-uri-58a034167 | U82: liadgo2@gmail.com | V82: +972546326372 | W82: Rare combination for Joulix: twice Israel Defense Prize for physics-based sensing + AI in complex sensor systems, then managed the Israeli Air Force's Energy Division (renewable energy, efficiency, IDF climate plan), Technion MSc in AI, Talpiot. Literal energy-management leadership + elite AI - the best conceptual match in cohort #3. Currently committed to a Weizmann PhD.
A83: 85 | B83: Mark Popov | D83: #3 | G83: Vayyar Imaging | H83: Chief Platform Innovation Officer | I83: Israel | J83: infra-systems | K83: B | T83: https://www.linkedin.com/in/mark-popov-92759b77 | U83: mark.popov@gmail.com | V83: +972544321050 | W83: C-level platform/innovation leadership at an RF-imaging chip company - real hardware-platform depth at a semiconductor player. Senior and committed; no GPU/power-software record.
A84: 87 | B84: Matan Shoef | D84: #3 | G84: OpenEyes | H84: Algorithms Team Lead | I84: Israel | J84: ai-ml | K84: B | T84: https://il.linkedin.com/in/matan-shoef-05a22a155 | U84: matan.shoef@gmail.com | V84: +972545221060 | W84: Algorithms team lead, ex-Samsung R&D, Technion EE. Solid algo engineering; no domain evidence.
A85: 84 | B85: Maya Kleinstein | D85: #3 | H85: Unknown | K85: C | U85: mayak144@gmail.com | V85: +972552242152 | W85: No LinkedIn in roster; no reliable public record found.
A86: 83 | B86: Maya Naveh | D86: #3 | H86: Unknown | K86: C | U86: maya.naveh.40@gmail.com | V86: +972504291882 | W86: No LinkedIn in roster; web search returned no reliable disambiguation.
A87: 86 | B87: Menachem Menasherov | D87: #3 | H87: Unknown | K87: C | U87: meny1237@gmail.com | V87: +972542338686 | W87: No LinkedIn in roster; no reliable public record found.
A88: 90 | B88: Nadav Claude Cohen | D88: #3 | H88: Stealth; reverse-engineering / binary-exploitation background | I88: Tel Aviv District, Israel | J88: security | K88: A | T88: https://www.linkedin.com/in/nadav-claude-cohen-8533b2a2/ | U88: nadav.claude.cohen@gmail.com | V88: +972543134989 | W88: Personal blog demonstrates real low-level depth (ASLR/PIE exploitation, RE). Profile shape of a systems engineer; currently at stealth; no verifiable GPU/power record.
A89: 89 | B89: Nadav Cohen | D89: #3 | G89: Tel Aviv University | H89: CTO at Imubit / Prof. of Computer Science & AI | I89: Houston, Texas, United States of America | J89: research | K89: C | T89: https://www.linkedin.com/in/dr-nadav-cohen-05575825a | U89: nadav@deepinsight.co.il | W89: If this is the Dr. Nadav Cohen of TAU/Imubit - whose company does deep-learning-based real-time control of large industrial facilities, optimizing them for profit and sustainability - it is conceptually the closest match in the entire roster: an RL control layer over physical infrastructure, monetized at scale (his Google Scholar even lists 'Physical AI' and RL). But the roster's LinkedIn slug does not match his known profiles and, if it is him, he is fully committed (professor + CTO). Verify identity before any outreach; would score ~92 on skills.
A90: 88 | B90: Noga Keren | D90: #3 | H90: Unknown | I90: Israel | K90: C | T90: https://www.linkedin.com/in/noga-keren | U90: noga.keren@gmail.com | V90: +972586110398 | W90: Web search returned no reliable public disambiguation for this name.
A91: 91 | B91: Noy Hadar | D91: #3 | G91: Breeze Security | I91: Tel Aviv District, Israel | J91: security | K91: C | T91: https://www.linkedin.com/in/noy-hadar-501870181 | U91: noyhadar95@gmail.com | V91: +972544826333 | W91: At Breeze Security (Dolev Elbaz's startup). No domain evidence.
A92: 64 | B92: Oren Fine | D92: #3 | G92: Stealth | H92: Founder | I92: Israel | J92: infra-systems | K92: A | T92: https://www.linkedin.com/in/orenfine2021/ | U92: orenfine@gmail.com | V92: +972586392129 | W92: Leads Israel-Innovation-Authority-funded research on ultrafast encrypted-traffic understanding powered by NVIDIA SmartNIC/DPU - genuinely close to modern GPU data-center infrastructure. Building his own stealth startup, so likely unavailable; strong advisor/partner candidate.
A93: 94 | B93: Oz Tamir | D93: #3 | F93: ARAM (Aramcon speaker) | H93: Builder; AI harness engineering speaker; embedded hobbyist | I93: Tel Aviv-Yafo, Tel Aviv District, Israel | J93: ai-ml | K93: C | T93: https://www.linkedin.com/in/oztamir/ | U93: oz@tamir.fun | V93: +972528645340 | W93: Prolific builder-generalist: talks on AI 'harness engineering' (built a Claude-Code-style agent harness from scratch), OSS incl. x86 assembly and ESP32/embedded projects. High-energy 0-to-1 engineer for the agentic tooling around the product; not a GPU/power-systems specialist.
A94: 97 | B94: Shlomo Lahav | D94: #3 | G94: TrueNorth Systems | H94: Co-Founder & CTO | I94: Israel | K94: A | T94: https://il.linkedin.com/in/shlomolahav | U94: shlomo@lahavs.com | V94: +972545330111 | W94: Long-tenured data-science leader (built LivePerson's sentiment/emotion engines), now founding his own company. Senior ML leadership; committed; no power/GPU record.
A95: 63 | B95: Uri Ariel Chen | D95: #3 | H95: Intel Granulate | I95: Tel Aviv District, Israel | J95: infra-systems | K95: C | T95: https://www.linkedin.com/in/uri-chen/ | U95: uriariel10@gmail.com | V95: +972549703632 | W95: At Intel Granulate - autonomous, real-time, agent-based workload/runtime optimization in production, acquired by Intel. This is the closest commercial analog to Joulix's value proposition (continuous compute-efficiency optimization), on the CPU side. Highest-priority screening call in cohort #3. (Minor caveat: roster slug differs from the public profile found; verify same person.)
A96: 80 | B96: Yaniv Shaked | D96: #3 | G96: Samsung Israel | H96: Stealth; ex-Computer Vision Group Leader | I96: Israel | J96: ai-ml | K96: A | T96: https://www.linkedin.com/in/yaniv-shaked-201b6540/ | U96: yanivsh002@gmail.com | V96: +972525621097 | W96: Led Samsung Israel's computer-vision group; now at a stealth startup. Strong algo leadership; CV domain, availability unclear.
A97: 79 | B97: Yoni Hornstein | D97: #3 | G97: Wiz | H97: Software Engineer | I97: Tel Aviv-Yafo, Tel Aviv District, Israel | J97: security | K97: C | T97: https://il.linkedin.com/in/yoni-hornstein-082177156 | U97: yoni.horn@gmail.com | V97: +972502758710 | W97: SWE at Wiz. No domain evidence.
A98: 78 | B98: Yuval Genossar | D98: #3 | G98: Government of Israel | H98: Head of R&D Section | Talpiot | I98: Tel Aviv-Yafo, Tel Aviv District, Israel | K98: C | T98: https://www.linkedin.com/in/yuvalgenossar | U98: yuval.genossar@gmail.com | V98: +972547260186 | W98: Web search returned no reliable public disambiguation (results match a different academic).

Sheet KPI Tracker
A1: Weekly KPIs
A2: §17 — not every number rises every week. We are looking for trend and quality. Grey columns compute themselves from the Call Schedule and the Roster; yellow ones you fill in on Thursday.
A4: Week of | B4: Qtr | C4: Calls planned | D4: Calls done | E4: Alumni info updated | F4: Quality connections | G4: Connections → outcome | H4: Alumni who helped an alum | I4: Office Hours contributors | J4: New SF relationships | K4: Moved Avishag → Nadav | L4: Needed Avishag | M4: What I learned / recommend
A5: Weekly target | D5: 4 | E5: 4 | F5: 3 | G5: 1 | H5: 2 | I5: 1 | J5: 1 | K5: 2 | L5: 2
A6: 46271 | B6: Q1 | C6: =COUNTIFS('Call Schedule'!$A$2:$A$190,">="&$A6,'Call Schedule'!$A$2:$A$190,"<="&$A6+6) | D6: =COUNTIFS('Call Schedule'!$A$2:$A$190,">="&$A6,'Call Schedule'!$A$2:$A$190,"<="&$A6+6,'Call Schedule'!$L$2:$L$190,"done") | E6: =COUNTIFS(Roster!$P$2:$P$98,">="&$A6,Roster!$P$2:$P$98,"<="&$A6+6)
A7: 46278 | B7: Q1 | C7: =COUNTIFS('Call Schedule'!$A$2:$A$190,">="&$A7,'Call Schedule'!$A$2:$A$190,"<="&$A7+6) | D7: =COUNTIFS('Call Schedule'!$A$2:$A$190,">="&$A7,'Call Schedule'!$A$2:$A$190,"<="&$A7+6,'Call Schedule'!$L$2:$L$190,"done") | E7: =COUNTIFS(Roster!$P$2:$P$98,">="&$A7,Roster!$P$2:$P$98,"<="&$A7+6)
A8: 46285 | B8: Q1 | C8: =COUNTIFS('Call Schedule'!$A$2:$A$190,">="&$A8,'Call Schedule'!$A$2:$A$190,"<="&$A8+6) | D8: =COUNTIFS('Call Schedule'!$A$2:$A$190,">="&$A8,'Call Schedule'!$A$2:$A$190,"<="&$A8+6,'Call Schedule'!$L$2:$L$190,"done") | E8: =COUNTIFS(Roster!$P$2:$P$98,">="&$A8,Roster!$P$2:$P$98,"<="&$A8+6)
A9: 46299 | B9: Q1 | C9: =COUNTIFS('Call Schedule'!$A$2:$A$190,">="&$A9,'Call Schedule'!$A$2:$A$190,"<="&$A9+6) | D9: =COUNTIFS('Call Schedule'!$A$2:$A$190,">="&$A9,'Call Schedule'!$A$2:$A$190,"<="&$A9+6,'Call Schedule'!$L$2:$L$190,"done") | E9: =COUNTIFS(Roster!$P$2:$P$98,">="&$A9,Roster!$P$2:$P$98,"<="&$A9+6)
A10: 46306 | B10: Q1 | C10: =COUNTIFS('Call Schedule'!$A$2:$A$190,">="&$A10,'Call Schedule'!$A$2:$A$190,"<="&$A10+6) | D10: =COUNTIFS('Call Schedule'!$A$2:$A$190,">="&$A10,'Call Schedule'!$A$2:$A$190,"<="&$A10+6,'Call Schedule'!$L$2:$L$190,"done") | E10: =COUNTIFS(Roster!$P$2:$P$98,">="&$A10,Roster!$P$2:$P$98,"<="&$A10+6)
A11: 46313 | B11: Q1 | C11: =COUNTIFS('Call Schedule'!$A$2:$A$190,">="&$A11,'Call Schedule'!$A$2:$A$190,"<="&$A11+6) | D11: =COUNTIFS('Call Schedule'!$A$2:$A$190,">="&$A11,'Call Schedule'!$A$2:$A$190,"<="&$A11+6,'Call Schedule'!$L$2:$L$190,"done") | E11: =COUNTIFS(Roster!$P$2:$P$98,">="&$A11,Roster!$P$2:$P$98,"<="&$A11+6)
A12: 46320 | B12: Q1 | C12: =COUNTIFS('Call Schedule'!$A$2:$A$190,">="&$A12,'Call Schedule'!$A$2:$A$190,"<="&$A12+6) | D12: =COUNTIFS('Call Schedule'!$A$2:$A$190,">="&$A12,'Call Schedule'!$A$2:$A$190,"<="&$A12+6,'Call Schedule'!$L$2:$L$190,"done") | E12: =COUNTIFS(Roster!$P$2:$P$98,">="&$A12,Roster!$P$2:$P$98,"<="&$A12+6)
A13: 46327 | B13: Q1 | C13: =COUNTIFS('Call Schedule'!$A$2:$A$190,">="&$A13,'Call Schedule'!$A$2:$A$190,"<="&$A13+6) | D13: =COUNTIFS('Call Schedule'!$A$2:$A$190,">="&$A13,'Call Schedule'!$A$2:$A$190,"<="&$A13+6,'Call Schedule'!$L$2:$L$190,"done") | E13: =COUNTIFS(Roster!$P$2:$P$98,">="&$A13,Roster!$P$2:$P$98,"<="&$A13+6)
A14: 46334 | B14: Q1 | C14: =COUNTIFS('Call Schedule'!$A$2:$A$190,">="&$A14,'Call Schedule'!$A$2:$A$190,"<="&$A14+6) | D14: =COUNTIFS('Call Schedule'!$A$2:$A$190,">="&$A14,'Call Schedule'!$A$2:$A$190,"<="&$A14+6,'Call Schedule'!$L$2:$L$190,"done") | E14: =COUNTIFS(Roster!$P$2:$P$98,">="&$A14,Roster!$P$2:$P$98,"<="&$A14+6)
A15: 46341 | B15: Q1 | C15: =COUNTIFS('Call Schedule'!$A$2:$A$190,">="&$A15,'Call Schedule'!$A$2:$A$190,"<="&$A15+6) | D15: =COUNTIFS('Call Schedule'!$A$2:$A$190,">="&$A15,'Call Schedule'!$A$2:$A$190,"<="&$A15+6,'Call Schedule'!$L$2:$L$190,"done") | E15: =COUNTIFS(Roster!$P$2:$P$98,">="&$A15,Roster!$P$2:$P$98,"<="&$A15+6)
A16: 46348 | B16: Q1 | C16: =COUNTIFS('Call Schedule'!$A$2:$A$190,">="&$A16,'Call Schedule'!$A$2:$A$190,"<="&$A16+6) | D16: =COUNTIFS('Call Schedule'!$A$2:$A$190,">="&$A16,'Call Schedule'!$A$2:$A$190,"<="&$A16+6,'Call Schedule'!$L$2:$L$190,"done") | E16: =COUNTIFS(Roster!$P$2:$P$98,">="&$A16,Roster!$P$2:$P$98,"<="&$A16+6)
A17: 46355 | B17: Q1 | C17: =COUNTIFS('Call Schedule'!$A$2:$A$190,">="&$A17,'Call Schedule'!$A$2:$A$190,"<="&$A17+6) | D17: =COUNTIFS('Call Schedule'!$A$2:$A$190,">="&$A17,'Call Schedule'!$A$2:$A$190,"<="&$A17+6,'Call Schedule'!$L$2:$L$190,"done") | E17: =COUNTIFS(Roster!$P$2:$P$98,">="&$A17,Roster!$P$2:$P$98,"<="&$A17+6)
... A55: 46621 | B55: Q4 | C55: =COUNTIFS('Call Schedule'!$A$2:$A$190,">="&$A55,'Call Schedule'!$A$2:$A$190,"<="&$A55+6) | D55: =COUNTIFS('Call Schedule'!$A$2:$A$190,">="&$A55,'Call Schedule'!$A$2:$A$190,"<="&$A55+6,'Call Schedule'!$L$2:$L$190,"done") | E55: =COUNTIFS(Roster!$P$2:$P$98,">="&$A55,Roster!$P$2:$P$98,"<="&$A55+6)
A58: The funnel (§19)
A59: Counted off Tie strength in the Roster. Far more meaningful than 'I did 17 calls'. Early on it will look thin — report it thin.
A61: Alumni | B61: Known | C61: Connected | D61: Engaged | E61: Contributor | F61: Node
A62: =COUNTA(Roster!$B$2:$B$98) | B62: =COUNTIF(Roster!$L$2:$L$98,"Known") | C62: =COUNTIF(Roster!$L$2:$L$98,"Connected") | D62: =COUNTIF(Roster!$L$2:$L$98,"Engaged") | E62: =COUNTIF(Roster!$L$2:$L$98,"Contributor") | F62: =COUNTIF(Roster!$L$2:$L$98,"Node")
A64: Dependency on Avishag (§18)
A65: What share of the week's items closed without her. 100% is not the goal — less over time is.
A67: Items handled this week
A68: Of those, closed without Avishag
A69: % handled independently | B69: =IF($B67=0,0,$B68/$B67)
A72: Three lines, every Thursday (§21)
A73: מה למדתי — what did I learn about our people this week?
A74: מה אני ממליץ — what should APEX do about it?
A75: מה אני צריך מאבישג — max three. Zero is better.

Sheet Q1 90-Day Test
A1: The 90-day test
A2: §24 — in ninety days these must be answerable without asking anyone. Q1 is built backwards from them. Deadline: 30 Nov 2026.
A4: # | B4: The question §24 asks | C4: What has to exist for it to be answerable | D4: Where it is tracked | E4: Status
A5: 1 | B5: Who are our 20 strongest alumni? | C5: All 27 tier-A alumni called at least once | D5: Call Schedule, filter Tier = A
A6: 2 | B6: What is each of them doing right now? | C6: Now / current goal filled for every tier-A row | D6: Roster, column M
A7: 3 | B7: Who is on the way to founding? | C7: The founding-track question asked on every tier-A call | D7: Roster, Notes + Now
A8: 4 | B8: What does each of them need? | C8: Needs filled for every tier-A row | D8: Roster, column N
A9: 5 | B9: What can each of them help with? | C9: Can help with filled for every tier-A row | D9: Roster, column O
A10: 6 | B10: Who already helps others? | C10: Tie strength set to Contributor or Node where true | D10: Roster, column L
A11: 7 | B11: Who are our people in SF? | C11: SF phases 1–2 done — circle mapped, key people met | D11: Projects sheet
A12: 8 | B12: Do we have the first 20 Office Hours contributors? | C12: 8 recruited by 30 Nov, with the anti-abuse model researched first | D12: Projects sheet
A13: 9 | B13: Which relationships moved from Avishag to Nadav? | C13: Counted weekly from week one, so a trend exists by Q4 | D13: KPI Tracker, column K
A14: 10 | B14: The 16 alumni with no verified role | C14: Role and company established for each | D14: Roster, filter Role = blank
A15: 11 | B15: If Avishag vanished for a month, would the network keep strengthening? | C15: The honest answer, written down | D15: Thursday report
B17: Tier-A calls completed | C17: =COUNTIFS('Call Schedule'!$G$2:$G$190,"A",'Call Schedule'!$L$2:$L$190,"done")
B18: Roster rows with Needs filled | C18: =COUNTA(Roster!$N$2:$N$98)
B19: Roster rows still with no verified role | C19: =COUNTIF(Roster!$H$2:$H$98,"Unknown*")

Sheet Projects
A1: Standing projects
A2: §9–§12. Dates are the plan's; owners and status are yours.
A4: Project | B4: What it is | C4: Target | D4: When | E4: Status | F4: Notes
A5: Alumni Roll-Up | B5: A live picture of every alum — not a list of names. Done when every row carries role, company, current goal and a next action. | C5: 16 unknowns → 0 | D5: By 30 Nov 2026
A6: Coffee Club #1 | B6: Four alumni, one per cohort, plus Avishag and Nadav. Listen through them, and start making each one active in the network. Nobody repeats within the year. Not called Coffee Club out loud. | C6: 4 alumni | D6: Early Oct 2026
A7: Coffee Club #2 | B7: As above — follow-ups from #1 owned by Nadav. | C7: 4 alumni | D7: Early Dec 2026
A8: Coffee Club #3 | B8: As above. | C8: 4 alumni | D8: Feb 2027
A9: Coffee Club #4 | B9: As above. | C9: 4 alumni | D9: Apr 2027
A10: Coffee Club #5 | B10: As above. | C10: 4 alumni | D10: Jun 2027
A11: Coffee Club #6 | B11: As above — closes the cycle with all cohorts. | C11: 4 alumni | D11: Aug 2027
A12: SF · phase 1 | B12: Map the existing circle. | C12: Circle mapped | D12: Q1
A13: SF · phase 2 | B13: Meet the people who matter in it. | C13: Key people met | D13: Q1
A14: SF · phase 3 | B14: Create value there, and stay warm when we need nothing from them. The phase that gets skipped, and the one that decides whether the network is real. | C14: Relationships held | D14: Q2
A15: SF · phase 4 | B15: Extend beyond Avishag's circle. An alum landing in SF walks into an existing network, not a strange city. | C15: Network beyond her | D15: Q3–Q4
A16: Office Hours · research | B16: How other networks run office hours, and above all how they prevent abuse, overload and contributor burnout. Check access, matching, frequency, quality control, fatigue, confidentiality, follow-up. Bring a recommendation, not a launch. | C16: A recommendation | D16: Q1, before launch
... A19: Month without Avishag | B19: Run the §24 test for real, and answer honestly whether the network kept strengthening. | C19: An honest answer | D19: Q4
A21: The introduction gate (§3)
A22: Before connecting two people, answer: why do these two need to know each other now? No good answer, no introduction. The goal is relationships that produce value, not a count of intros. And close the loop with the alum — even when Avishag does not reply, Delgo is the one who makes sure the circle closes.
